pyanypay/__init__.py
pyanypay/api.py
pyanypay/exceptions/__init__.py
pyanypay/exceptions/code_exception.py
pyanypay/types/__init__.py
pyanypay/types/literals.py
pyanypay/types/responses.py
pyanypay-0.1.0.dist-info/LICENSE
pyanypay-0.1.0.dist-info/WHEEL
pyanypay-0.1.0.dist-info/METADATA
pyanypay-0.1.0.dist-info/RECORD
